brzcoding/__init__.py
brzcoding/brzcode.py
brzcoding-1.0.0.dist-info/WHEEL
brzcoding-1.0.0.dist-info/METADATA
brzcoding-1.0.0.dist-info/RECORD
