Metadata-Version: 2.1
Name: brzcoding
Version: 1.0.0
Summary: Programação simples, veloz e sem complicações
Author: Gustavo Martinez
Author-email: gamezinhoo@outlook.com
Requires-Python: >=3.9,<4.0
Classifier: Programming Language :: Python :: 3
Classifier: Programming Language :: Python :: 3.10
Classifier: Programming Language :: Python :: 3.9
